[
  {
    "source": "전기신문",
    "title": "한전KDN, 완주 AI 데이터센터 구축 협약…에너지·ICT 통합 설계 주도",
    "url": "https://www.electimes.com/news/articleView.html?idxno=365651",
    "date": "2026-03-03",
    "tags": [
      "수소",
      "재생에너지",
      "ESS",
      "데이터센터",
      "전력계통"
    ],
    "subtitle": "재생에너지·ESS·AI 기반 운영체계 설계…40MW급 고효율·고안정 인프라 구축 에너지ICT 전문 공기업 한전KDN(사장 박상형)이 지난 2월 26일 완주군청 군수실에서 에너지허브형 데이터센터 구축을 위한 ‘완주 AI 데이터센터 구축 협약’을 진행했다고 3일 밝혔다. 협약식에는 최진수 한전KDN 신사업개발본부장을 비롯한 유희태 완주군수, 안효중 테크노그린 대표, 조주완 LG전자 대표 등 관계자들이 참석했다.",
    "is_important": 1
  },
  {
    "source": "전기신문",
    "title": "한재연, 최재관 신임 에너지공단 이사장에 ‘재생에너지 대전환’ 실무協 제안",
    "url": "https://www.electimes.com/news/articleView.html?idxno=365648",
    "date": "2026-03-03",
    "tags": [
      "재생에너지",
      "RE100"
    ],
    "subtitle": "한국재생에너지단체총연합회(회장 권영호, 한재연)는 3일 컨퍼런스하우스 달개비에서 최재관 신임 한국에너지공단 이사장과 오찬 간담회를 개최했다고 밝혔다. 이날 간담회는 앞서 한재연의 공동대표를 역임한 최재관 한국에너지공단 신임 이사장의 취임을 축하하기 위해 마련됐다.",
    "is_important": 1
  },
  {
    "source": "전기신문",
    "title": "케이베츠, 해상풍력 재킷 핵심 기술 ‘그립퍼(Gripper)’ 장관상 수상",
    "url": "https://www.electimes.com/news/articleView.html?idxno=365629",
    "date": "2026-03-03",
    "tags": [
      "기후부"
    ],
    "subtitle": "해상풍력 설치 전문기업 케이베츠의 그립퍼(Gripper)가 기후에너지환경부 장관상을 수상하며 기술력을 인정받았다. 그립퍼는 대규모 해상풍력 단지에 적용되는 재킷 기초에 적용되고 있으며 지속적인 업그레이드를 통해 활용 분야를 넓혀나갈 계획이다.",
    "is_important": 1
  },
  {
    "source": "전기신문",
    "title": "남부발전, 인천 호랑에너지 연료전지 발전소 현장 안전경영",
    "url": "https://www.electimes.com/news/articleView.html?idxno=365654",
    "date": "2026-03-03",
    "tags": [
      "연료전지",
      "재생에너지"
    ],
    "subtitle": "윤상옥 전무, 준공 1주년 앞두고 안전관리 체계 및 운영현황 점검 ‘작업중지권’ 등 안전 확보 방안 남부발전이 인천 호랑에너지 연료전지 발전소의 안전관리체계와 운영현황을 점검했다. 3일 한국남부발전은 최근 인천 서구에 위치한 호랑에너지 연료전지 발전소(19.36MW)를 방문해 현장경영을 실시했다고 밝혔다.",
    "is_important": 1
  },
  {
    "source": "전기신문",
    "title": "“우리동네 기후환경정보 한눈에”…기후부, 모바일 서비스 확대",
    "url": "https://www.electimes.com/news/articleView.html?idxno=365632",
    "date": "2026-03-03",
    "tags": [
      "기후부",
      "충전소"
    ],
    "subtitle": "자외선지수 및 무공해차 충전소 위치 등 실시간 확인 가능 정부가 기후위기 시대에 국민이 일상 속 환경 정보를 보다 신속하고 편리하게 확인할 수 있는 기반을 마련했다. 기후에너지환경부는 기존에 웹 기반으로 제공되던 ‘우리동네 기후환경정보’를 모바일 환경에 최적화해 확대 운영한다고 3일 밝혔다.",
    "is_important": 1
  },
  {
    "source": "전기신문",
    "title": "‘중동 사태’로 커지는 긴장...석유·가스 수급 비상체계 가동",
    "url": "https://www.electimes.com/news/articleView.html?idxno=365646",
    "date": "2026-03-03",
    "tags": [
      "기후부"
    ],
    "subtitle": "산업부, 제3차 실물경제 점검회의 개최...대응 본부 차관급으로 격상 석유·가스 수급 현재까지 이상 無…해상물류 영향도 제한적 산업통상부는 김정관 장관이 ‘중동 상황’ 급변에 대응하기 위해 3일 필리핀 현지에서 화상 연결해 '제3차 실물경제 점검회의'를 개최하고, 자원·에너지 수급, 무역·공급망·금융 및 업종별 영향을 점검했다고 밝혔다. 이번 회의에는 외교부·기후부·해수부·금융위 등 관계부처와 석유공사·가스공사·코트라(중동본부)·에너지경제연구원, 대한상공회의소·한국경제인협회·한국무역협회 및 석유·화학·플랜트협회, 주미국·중국·일본·유럽연합(EU) 상무관 등이 참석했다.",
    "is_important": 1
  },
  {
    "source": "전기신문",
    "title": "[美-이란 전쟁] ‘중동의 물길’ 막혔다…리스크 커지는 LNG 수급",
    "url": "https://www.electimes.com/news/articleView.html?idxno=365628",
    "date": "2026-03-03",
    "tags": [
      "재생에너지"
    ],
    "subtitle": "호르무즈 리스크에 유럽 가스값 45% ↑…비축 물량 낮아 수급 경쟁 적신호 장기전 대비한 에너지 믹스 정비 목소리 커져…이념 중심 정책 개선 목소리 탈석탄 유지 괜찮나…가격 리스크 및 수급 안정 측면서 석탄화력 역할 필요 2일 이란혁명수비대(IRGC)가 호르무즈 해협 봉쇄를 본격 선언했다. 국내 LNG 수입의 20%를 차지하는 중동의 물길이 막히면서 전력시장의 변동성이 다시 부각되는 모습이다.",
    "is_important": 1
  },
  {
    "source": "전기신문",
    "title": "SGC에너지, AI 데이터센터 자회사 설립…300MW 발전소 결합형 프로젝트 본격화",
    "url": "https://www.electimes.com/news/articleView.html?idxno=365649",
    "date": "2026-03-03",
    "tags": [
      "데이터센터"
    ],
    "subtitle": "1단계 40MW 모듈형 센터 군산에 구축…2028년 1분기 운영 목표 이사회서 주당 1300원 현금배당·사외이사에 김종국 고려대 교수 내정 SGC에너지가 AI 데이터센터 사업을 위한 신규 법인 설립을 결정하고 본격적인 실행 단계에 돌입했다. SGC에너지는 3일 이사회를 열어 AI 데이터센터 사업 추진을 위한 신규 법인 출자 안건을 의결했다고 밝혔다.",
    "is_important": 1
  },
  {
    "source": "전기신문",
    "title": "EV 넘어 ESS·로봇·AI로...K-배터리 '미래 포트폴리오 다각화 격돌'",
    "url": "https://www.electimes.com/news/articleView.html?idxno=365645",
    "date": "2026-03-03",
    "tags": [
      "ESS",
      "배터리",
      "미코",
      "데이터센터"
    ],
    "subtitle": "11일 개막하는 인터배터리 2026 전시회 총출동 전기차 외에 다양한 포트폴리오 선봬...\"배터리가 AI 시대 심장\" 사전 어워드 행사서도 초격차 기술력 놓고 승부 ◆ EV 넘어 ESS·로봇·AI로...배터리 3사, 미래 포트폴리오 다각화 격돌 국내 최대 규모의 배터리 산업 전시회인 '인터배터리 2026' 개막이 임박했다. 오는 11일부터 서울 코엑스에서 열리는 이번 전시회는 배터리의 무한한 확장성을 직접 확인하는 계기가 될 전망이다.",
    "is_important": 1
  },
  {
    "source": "에너지신문",
    "title": "한국요꼬가와전기, 배터리 전 공정 디지털 혁신 선보인다",
    "url": "https://www.energy-news.co.kr/news/articleView.html?idxno=223309",
    "date": "2026-03-03",
    "tags": [
      "배터리"
    ],
    "subtitle": "[에너지신문] 한국요꼬가와전기(이하 요꼬가와)는 오는 11일부터 13일까지 서울 코엑스에서 열리는 국내 최대 배터리 산업 전시회 ‘InterBattery 2026’에 참가해 배터리 제조 전 공정을 아우르는 통합 디지털 전환(Digital Transformation, DX) 전략과 핵심 솔루션을 선보인다고 3일 밝혔다. 올해로 14회를 맞는 ‘InterBattery 2026’은 글로벌 배터리 산업의 최신 기술과 시장 트렌드를 한 자리에서 조망할 수 있는 대표 전시회로 배터리 셀 제조사부터 소재·부품·장비 기업까지 산업 전반의 주요 기업들이 대거 참여한다.",
    "is_important": 1
  },
  {
    "source": "에너지신문",
    "title": "태양광공사협회 “투자 환경 개선·산업 고도화 기대”",
    "url": "https://www.energy-news.co.kr/news/articleView.html?idxno=223341",
    "date": "2026-03-03",
    "tags": [
      "재생에너지",
      "탄소중립"
    ],
    "subtitle": "[에너지신문] 한국태양광공사협회가 \"최근 저탄소 태양광 기술에 대한 세제 지원 확대와 재생에너지 법체계 정비가 동시에 이뤄지면서, 국내 재생에너지 산업의 정책 환경이 구조적으로 개선되고 있다\"고 평가했다. 정부는 조세특례제한법 시행령 개정을 통해 '저탄소 태양광 모듈 설계·제조·설치기술'을 신성장·원천기술에 신규 반영했다.",
    "is_important": 1
  },
  {
    "source": "에너지신문",
    "title": "천안·아산·서산·당진 잇는 이차전지 특화단지 유치 나서",
    "url": "https://www.energy-news.co.kr/news/articleView.html?idxno=223307",
    "date": "2026-03-03",
    "tags": [
      "배터리",
      "미코"
    ],
    "subtitle": "[에너지신문] 충남도가 미래 국가 경제의 핵심 동력인 이차전지 산업의 주도권을 확보하고 지역 경제의 비약적인 도약을 이끌기 위해 ‘국가첨단전략산업 특화단지’ 유치에 나섰다. 충남도는 최근 천안·아산·서산·당진 등 서북부권 4개시와 국내외 이차전지 산업을 선도하는 주요 기업, 대학, 연구기관 등 총 16개 기관과 ‘국가첨단전략산업 특화단지 지정 협력 업무협약’을 체결했다고 3일 밝혔다.",
    "is_important": 1
  },
  {
    "source": "에너지신문",
    "title": "전북 완주 AI 데이터센터에 ‘LG 토털 HVAC 솔루션’ 공급한다",
    "url": "https://www.energy-news.co.kr/news/articleView.html?idxno=223329",
    "date": "2026-03-03",
    "tags": [
      "히트펌프",
      "데이터센터",
      "전력계통"
    ],
    "subtitle": "[에너지신문] LG전자가 냉난방공조(HVAC) 분야의 앞선 기술력을 기반으로 전북 완주군에 건립 예정인 AI 데이터센터에 데이터센터향 토털 냉각솔루션 공급을 추진한다. LG전자는 최근 전라북도 완주군, (주)테크노그린, 한전KDN(주)과 ‘완주 데이터센터 구축사업’ 추진을 위한 업무협약(MOU)을 체결했다.",
    "is_important": 1
  },
  {
    "source": "에너지신문",
    "title": "원자력환경공단, 고졸 일반직·비정규직 42명 채용",
    "url": "https://www.energy-news.co.kr/news/articleView.html?idxno=223340",
    "date": "2026-03-03",
    "tags": [
      "원자력"
    ],
    "subtitle": "[에너지신문] 한국원자력환경공단이 오는 18일까지 고졸 일반직, 휴직대체근로자, 체험형 인턴 등 총 42명의 직원을 공개 채용한다. 채용 인원은 일반직(고졸) 설비·계통 분야 8명이며 비정규직은 휴직 대체 기간제근로자 8명, 체험형 인턴 26명(청년 20명, 자립준비청년 4명, 장애인 2명) 등 총 34명이다.",
    "is_important": 1
  },
  {
    "source": "에너지신문",
    "title": "에너지공단-한재연, '재생E 대전환 실무협의회' 구성 합의",
    "url": "https://www.energy-news.co.kr/news/articleView.html?idxno=223344",
    "date": "2026-03-03",
    "tags": [
      "재생에너지"
    ],
    "subtitle": "[에너지신문] 에너지공단과 한국재생에너지단체총연합회(한재연)이 '재생에너지 대전환 추진 실무협의회'를 구성키로 합의했다. 민관 실무 협력 플렛폼 구축을 통한 '재생에너지 100GW 시대' 도약이라는 공감대를 형성한 것.",
    "is_important": 1
  },
  {
    "source": "에너지신문",
    "title": "엄중한 중동 상황에 대응조직 격상…김정관 장관, 실물경제 점검",
    "url": "https://www.energy-news.co.kr/news/articleView.html?idxno=223317",
    "date": "2026-03-03",
    "tags": [
      "기후부"
    ],
    "subtitle": "[에너지신문] 김정관 산업통상부 장관이 중동 상황의 급변에 대응해 3일 필리핀 현지에서 화상 연결을 통해 ‘제3차 실물경제 점검회의’를 개최하고 자원·에너지 수급, 무역·공급망·금융 및 업종별 영향을 점검했다. 중동상황을 엄중하게 판단해 현재 산업자원안보실장을 반장으로 하는 대응조직을 차관을 본부장으로 하는 ‘중동상황 대응본부로 격상하고 원유·가스 수급 위기관리 체제에 즉각 돌입하기로 했다.",
    "is_important": 1
  },
  {
    "source": "에너지신문",
    "title": "서울에너지드림센터, '찾아가는 에너지드림스쿨' 참여기관 모집",
    "url": "https://www.energy-news.co.kr/news/articleView.html?idxno=223343",
    "date": "2026-03-03",
    "tags": [
      "재생에너지",
      "탄소중립"
    ],
    "subtitle": "[에너지신문] 서울에너지드림센터가 탄소중립·재생에너지·제로에너지건축물(ZEB) 방문형 환경교육 프로그램 '찾아가는 에너지드림스쿨'의 참여기관을 모집한다. 에너지드림스쿨은 센터 방문이 어려운 기관을 직접 방문해 진행하는 환경교육 프로그램이다.",
    "is_important": 1
  },
  {
    "source": "에너지신문",
    "title": "삼성전자, AI 자율공장 전환 추진…2030년까지",
    "url": "https://www.energy-news.co.kr/news/articleView.html?idxno=223297",
    "date": "2026-03-03",
    "tags": [
      "ESS"
    ],
    "subtitle": "[에너지신문] 삼성전자가 2030년까지 국내외 생산 공장을 ‘AI 자율 공장(AI Driven Factory)’으로 전환하겠다고 밝혔다. AI 자율 공장은 제조 전 공정에 AI를 적극 적용한 공장이다.",
    "is_important": 1
  },
  {
    "source": "에너지신문",
    "title": "롯데에어리퀴드 에너하이, 안정수 신임 대표 선임",
    "url": "https://www.energy-news.co.kr/news/articleView.html?idxno=223301",
    "date": "2026-03-03",
    "tags": [
      "수소",
      "ESS"
    ],
    "subtitle": "[에너지신문] 롯데에어리퀴드 에너하이(Lotte-Air Liquide Ener'Hy)가 안정수 신임 대표이사를 선임했다. 롯데에어리퀴드 에너하이는 지난 1일부로 안정수 대표이사가 이사회와 주주총회의 의결을 거쳐 선임됐다고 밝혔다.",
    "is_important": 1
  },
  {
    "source": "에너지신문",
    "title": "대한민국 전기안전에 기여한 ‘숨은 주역’ 찾는다",
    "url": "https://www.energy-news.co.kr/news/articleView.html?idxno=223338",
    "date": "2026-03-03",
    "tags": [
      "재생에너지"
    ],
    "subtitle": "[에너지신문] 한국전기안전공사가 전기재해 예방과 국가 산업 발전에 기여한 공로자 발굴에 나선다. 전기안전공사는 '2026년 전기안전관리 유공자' 공모를 3일부터 오는 4월 15일까지 진행한다.",
    "is_important": 1
  },
  {
    "source": "에너지신문",
    "title": "[에너지논단] 탄소중립 선도 에너지전환, 기계공학이 설계한다",
    "url": "https://www.energy-news.co.kr/news/articleView.html?idxno=223312",
    "date": "2026-03-03",
    "tags": [
      "수소",
      "연료전지",
      "그린수소",
      "히트펌프",
      "수전해",
      "CCU",
      "CCUS",
      "ESS",
      "충전소",
      "수소차",
      "RE100",
      "데이터센터",
      "AI데이터센터",
      "탄소중립",
      "수소경제"
    ],
    "subtitle": "[에너지신문] 탄소중립은 이제 선택이 아니라 생존의 조건이다. 2050 탄소중립, RE100, EU CBAM(탄소국경조정제도)은 더이상 선언이 아니라 실행 기준이 됐다.",
    "is_important": 1
  },
  {
    "source": "에너지신문",
    "title": "DL이앤씨, 양수발전 시장 공략...독보적 기술 뽐낸다",
    "url": "https://www.energy-news.co.kr/news/articleView.html?idxno=223315",
    "date": "2026-03-03",
    "tags": [
      "재생에너지"
    ],
    "subtitle": "[에너지신문] DL이앤씨가 양수발전에 특화된 기술력을 앞세워 시장 공략에 본격적으로 나선다. DL이앤씨는 지하 100m 이상 대심도 수직터널을 효율적으로 시공할 수 있는 ‘양수발전 특화 슬립폼(콘크리트를 부을 때 모양을 잡아주는 틀)’ 공법을 개발, 특허를 내고 상용화를 추진 중이라고 3일 밝혔다.",
    "is_important": 1
  },
  {
    "source": "에너지신문",
    "title": "'RPS→계약시장' 전환, 재생E 발전단가 하락 어려워",
    "url": "https://www.energy-news.co.kr/news/articleView.html?idxno=223336",
    "date": "2026-03-03",
    "tags": [
      "재생에너지",
      "RPS"
    ],
    "subtitle": "[에너지신문] 정부가 신재생에너지 공급의무화(RPS) 제도를 없애고 계약시장(입찰) 제도로 전환을 추진하고 있지만, 이를 통해 재생에너지 발전단가를 낮추거나 특정 에너지 쏠림 문제를 해결하기 어렵다는 분석이 나왔다. 3일 사단법인 넥스트는 최근 발행한 보고서 'RPS 제도 전환, 설계는 목표에 부합하는가'에서 \"정부는 신재생에너지 RPS 제도를 폐지하고 재생에너지 설비 계약시장 제도로 전환하겠다는 계획을 공식화했다\"며 \"이를 위한 신에너지 및 재생에너지 개발·이용·보급 촉진법(재생에너지법) 개정안이 발의됐다\"고 설명했다.",
    "is_important": 1
  },
  {
    "source": "가스신문",
    "title": "산업부 차관 주재 ‘이란 사태’ 실물경제 영향 긴급 점검",
    "url": "https://www.gasnews.com/news/articleView.html?idxno=124148",
    "date": "2026-03-03",
    "tags": [
      "기후부"
    ],
    "subtitle": "[가스신문 = 유재준 기자]산업통상부(이하 산업부) 문신학 차관은 지난달 28일 미국·이스라엘의 이란 타격으로 중동지역 불안이 확산됨에 따라, 지난 1일 외교부·기후부·해수부·금융위 등 관계부처와 석유공사·가스공사·코트라(중동본부)·에너지경제연구원, 대한상공회의소·한국경제인협회·한국무역협회 및 업종별 협·단체(석유협회·화학협회·플랜트협회 등), 주미국·중국·일본·유럽연합(EU) 상무관 등이 참석한 가운데 ‘제2차 실물경제 점검회의’를 개최하고, 자원·에너지 수급, 무역·공급망·금융 및 업종별 영향을 점검했다. 사태 발생 당일인 28일 김정관 산업부 장관이 자원 수급과 국내 업계 영향 등을 긴급 점검한 데 이어, 이날 회의는 통상·무역·자원·안보 등 실물경제 영향과 대응방안을 점검하기 위해 개최한 것이다.",
    "is_important": 1
  },
  {
    "source": "가스신문",
    "title": "롯데-에어리퀴드 에너하이 새 대표에 안정수 씨 선임",
    "url": "https://www.gasnews.com/news/articleView.html?idxno=124149",
    "date": "2026-03-03",
    "tags": [
      "수소",
      "ESS"
    ],
    "subtitle": "[가스신문 = 한상열 기자] 롯데에어리퀴드 에너하이(Lotte-Air Liquide Ener'Hy)는 듀폰코리아, 머크코리아 등의 글로벌 화학회사에서 공정 및 프로젝트 엔지니어, 프로덕트 매니저, 사업 개발 매니저 등으로 활약한 안정수 씨를 신임 대표이사로 선임했다. 안정수 신임 대표는 2019년 에어리퀴드코리아 Large Industries(LI) 사업부에 합류하여 현재 LI 사업부 및 한국 대외협력 업무 부사장을 겸직하였다.",
    "is_important": 1
  },
  {
    "source": "가스신문",
    "title": "기후부, 취약계층 연탄사용가구 고효율에너지로 전환 지원",
    "url": "https://www.gasnews.com/news/articleView.html?idxno=124138",
    "date": "2026-03-03",
    "tags": [
      "기후부"
    ],
    "subtitle": "[가스신문 = 양인범 기자] 기후에너지환경부(장관 김성환)와 기획예산처(장관직무대행 차관 임기근), 산업통상부(장관 김정관)는 3일부터 연탄쿠폰 수급가구의 고효율 에너지로의 전환을 지원하는 패키지 사업을 본격 추진한다. 이는 지난해 8월 13일 대통령 주재 나라재정절약간담회에서 연탄생산보조금의 에너지바우처 전환방안을 논의한 데 따른 후속 조치로 추진하는 사업이다.",
    "is_important": 1
  },
  {
    "source": "가스신문",
    "title": "구미·칠곡 1900억원 규모 광역 바이오가스화 민자사업 심의 통과",
    "url": "https://www.gasnews.com/news/articleView.html?idxno=124150",
    "date": "2026-03-03",
    "tags": [
      "바이오가스"
    ],
    "subtitle": "[가스신문 = 양인범 기자] 경북 구미시에 들어서는 ‘광역 통합 바이오가스화 시설’ 사업이 최근 민간투자사업 심의를 통과했다. 기획예산처는 2026년도 제1차 민간투자사업심의위원회(민투심)를 열어 구미시 광역 통합바이오가스화시설 실시협약안을 심의·의결했다고 밝혔다.",
    "is_important": 1
  },
  {
    "source": "가스신문",
    "title": "가스안전공사 경북북부지사, 재난안전 실천 다짐",
    "url": "https://www.gasnews.com/news/articleView.html?idxno=124140",
    "date": "2026-03-03",
    "tags": [
      "수소"
    ],
    "subtitle": "[가스신문 = 이경인 기자] 한국가스안전공사 경북북부지사(지사장 이동엽)는 2월 27일 한국열관리시공협회 주관 2026 에너지 절약 및 재난안전관리 실천 다짐대회를 방문, 박경국 사장을 대신하여 2025년도 가스사고 예방에 기여한 협회 소속 3명의 유공자에 대해 포상을 전달했다. 가스안전공사 사장(박경국) 표창은 한국열관리시공협회 안동지회 소속 대창수도보일러공사 대표 김수태, 영덕·울진지회 동명종합설비 정재삼 대표, 문경·예천지회 중앙설비공사 김영철 대표 등 3명에게 수여됐다.",
    "is_important": 1
  },
  {
    "source": "가스신문",
    "title": "‘셀프 LPG충전은 이렇게’",
    "url": "https://www.gasnews.com/news/articleView.html?idxno=124152",
    "date": "2026-03-03",
    "tags": [
      "충전소"
    ],
    "subtitle": "[가스신문 = 이경인 기자] 한국가스안전공사 경기북부지사장(송제웅)은 27일, 경기도 포천시 내촌면 소재 ‘행복금강로 충전소(셀프충전소)’를 방문하여 셀프 LPG충전소 안전관리 실태를 점검했다. 이번 점검은 지난해 11월 액화석유가스의 안전관리 및 사업법 개정·공포에 따라 셀프충전 제도가 본격 시행되면서 현장 안전관리 이행상황을 확인하고 사업자의 자율안전관리 강화를 독려하기 위해 실시됐다.",
    "is_important": 1
  },
  {
    "source": "가스신문",
    "title": "[인터뷰] 한국탄소산업진흥원 수소저장용기 시험인증센터 정근성 센터장 “수소용기 업계 및 기술 발전 기여할 터”",
    "url": "https://www.gasnews.com/news/articleView.html?idxno=124142",
    "date": "2026-03-03",
    "tags": [
      "수소",
      "연료전지",
      "수소저장"
    ],
    "subtitle": "[가스신문 = 박귀철 기자] “수소저장용기 시험인증센터는 수소저장용기 기술 상용화의 가장 큰 걸림돌이었던 인증시험에 따른 기업 부담을 줄이기 위한 목적으로 추진됐습니다. 수소용기 제조업체 및 전문가들로부터 다양한 의견을 수렴했으며, 그들의 적극적인 협조와 진흥원 직원들의 노력 덕분에 원활히 준공될 수 있었습니다.",
    "is_important": 1
  },
  {
    "source": "가스신문",
    "title": "3월부터 도시가스용 천연가스 도매요금 인하",
    "url": "https://www.gasnews.com/news/articleView.html?idxno=124147",
    "date": "2026-03-03",
    "tags": [
      "연료전지",
      "도시가스"
    ],
    "subtitle": "[가스신문 = 주병국 기자] 3개월 연속 인상된 도시가스용 천연가스 도매요금이 3월부터 인하됐다. 한국가스공사는 천연가스(LNG) 원료비가 국제 유가와 환율 변동에 따라 3월부터 도시가스용 평균 도매요금을 18.8852원/MJ에서 18.6364원/MJ으로 종전보다 0.2488원/MJ 인하했다고 밝혔다.",
    "is_important": 1
  },
  {
    "source": "가스신문",
    "title": "3월 국내 LPG가격 25~28원/kg '↑'···큰폭 인상요인에도 ‘물가안정’ 고려",
    "url": "https://www.gasnews.com/news/articleView.html?idxno=124133",
    "date": "2026-03-03",
    "tags": [
      "충전소"
    ],
    "subtitle": "[가스신문 = 김재형 기자] 3월 국내 LPG가격이 큰 폭의 인상요인에도 불구하고 kg당 25~28원 인상에 그쳤다. LPG수입사들이 정부의 물가안정 기조에 동참하며 가격 인상을 최소화한 것으로 풀이된다.",
    "is_important": 1
  }
]