[
  {
    "source": "전기신문",
    "title": "창립 50년 전기연구원, 전기 학계와 미래 100년 머리 맞대다",
    "url": "https://www.electimes.com/news/articleView.html?idxno=370214",
    "date": "2026-07-11",
    "tags": [
      "재생에너지",
      "전력계통"
    ],
    "subtitle": "대한전기학회 하계학술대회 연계 전문가 포럼 개최 KERI 역할과 산·학·연 협력 방향 모색 한국전기연구원(KERI)은 9일 강원도 평창 용평리조트에서 열린 대한전기학회 하계학술대회와 연계해 'KERI 창립 50주년 전문가 포럼'을 개최했다고 밝혔다. 올해 창립 50주년을 맞은 KERI는 오는 11월 메인 기념식을 앞두고 매월 다양한 온·오프라인 행사를 통해 국민과 소통하고 있다.",
    "is_important": 1
  },
  {
    "source": "전기신문",
    "title": "경남 산단서 만든 전기, 기업·근로자에 돌려준다...'햇빛소득' 본격화",
    "url": "https://www.electimes.com/news/articleView.html?idxno=370215",
    "date": "2026-07-11",
    "tags": [
      "연료전지",
      "재생에너지",
      "충전소",
      "바이오가스"
    ],
    "subtitle": "마산자유무역지역·사천일반산단 643억원 투입...국비 400억원 확보 태양광·EMS 구축, 저렴한 전력 공급...2030년 산단 태양광 설치율 35% 목표 경남지역 산업단지의 에너지 자립과 저탄소 전환에 속도가 붙는다. 마산자유무역지역과 사천일반산업단지에 태양광과 에너지관리시스템(EMS) 등 분산에너지 인프라를 구축하고, 발전 수익을 입주기업과 근로자에게 돌려주는 '햇빛소득' 모델도 도입한다.",
    "is_important": 1
  },
  {
    "source": "전기신문",
    "title": "[우주가 월가를 흔들다](中)로켓 너머의 우주산업…인프라·통신·데이터 3파전",
    "url": "https://www.electimes.com/news/articleView.html?idxno=370116",
    "date": "2026-07-11",
    "tags": [
      "데이터센터"
    ],
    "subtitle": "위성 제작 시장, 4년 새 120억→200억 달러로 껑충 통신사들의 반격…위성과 지상망 잇는 하이브리드망 위성 데이터, 농업·보험의 의사결정 도구로 진화 3대 축이 그리는 2035년 약 2692조원 규모 지도 상편에서 짚었던 스페이스X의 급등락은 우주산업이 자본시장의 주류로 편입됐다는 신호였다. 그렇다면 이 시장에서 실제로 돈을 버는 구조는 무엇일까.",
    "is_important": 1
  },
  {
    "source": "전기신문",
    "title": "LH-한난, 공공임대주택 에너지 효율 향상 맞손",
    "url": "https://www.electimes.com/news/articleView.html?idxno=370216",
    "date": "2026-07-11",
    "tags": [
      "탄소중립"
    ],
    "subtitle": "노후 열공급 시설 개선으로 입주민 주거비 부담 낮춘다 한국토지주택공사(LH)가 한국지역난방공사(한난)와 손잡고 공공임대주택의 에너지 효율 개선에 나선다. LH는 한난과 ‘공공임대주택 열효율 향상 및 에너지 절감을 위한 업무협약(MOU)’을 체결했다고 지난 10일 밝혔다.",
    "is_important": 1
  },
  {
    "source": "에너지신문",
    "title": "가스안전공사 인천본부, 암모니아 누출사고 대응 훈련",
    "url": "https://www.energy-news.co.kr/news/articleView.html?idxno=226742",
    "date": "2026-07-11",
    "tags": [
      "암모니아"
    ],
    "subtitle": "[에너지신문] 한국가스안전공사 인천본부(본부장 김은정)는 10일 인천 영종구 소재 인천공항에너지에서 암모니아 가스 누출사고 대응 합동훈련을 실시했다. 이번 훈련은 가스안전공사, 인천공항에너지 자위소방대원 등 관계자 약 40여명이 참석한 가운데 암모니아 시설의 잠재적 가스사고를 선제 예방하고 사고발생시 신속한 상황전파 및 긴급복구 능력을 향상시키기 위해 실시됐다.",
    "is_important": 1
  }
]