[
  {
    "source": "전기신문",
    "title": "한수원, 협력社와 미국 원전시장 공략…최대 전시회 참여",
    "url": "https://www.electimes.com/news/articleView.html?idxno=364401",
    "date": "2026-01-22",
    "tags": [
      "원자력",
      "한수원"
    ],
    "subtitle": "파워젠 전시회 참석 등 ‘MANUGA with K’ 사업 추진 한수원이 협력 중소기업의 북미 시장 진출을 돕기 위해 현지에서 지원활동을 펼쳤다. 22일 한국수력원자력은 지난 18일부터 오는 24일(현지시간)까지 16개 협력 중소기업과 미국 텍사스주에서 ‘MANUGA with K’ 사업을 통해 미국 원전산업 선점을 위한 지원활동을 펼치고 있다고 밝혔다.",
    "is_important": 1
  },
  {
    "source": "전기신문",
    "title": "충전인프라 정책 개편안 놓고 업계선 \"방향에는 공감\", \"예산·실행 가능성은 걱정”",
    "url": "https://www.electimes.com/news/articleView.html?idxno=364405",
    "date": "2026-01-22",
    "tags": [
      "기후부",
      "탄소중립"
    ],
    "subtitle": "기후부 '2026 충전 인프라 보조금사업' 개편안 발표 운영·제조 분리 평가·선정에 대해선 긍정적 반응 예산 12% 삭감·파워모듈 평가는 시기상조 지적 취득세·A/S 등 책임 소재 불명확…세부 지침 시급 기후에너지환경부가 22일 발표한 2026년 전기차 충전 인프라 보조금 사업 개편안을 두고 업계가 방향성에는 공감을 표하면서도 현실적 과제에 대해서는 우려의 목소리를 내고 있다. 기후부는 올해 예산 5457억원을 지원해 급속 4450기, 중속 2000기, 완속 6만5000기 등 총 7만1450기 설치를 지원한다고 밝혔다.",
    "is_important": 1
  },
  {
    "source": "전기신문",
    "title": "전력거래소, 재생에너지 준중앙급전 운영제도 봄철부터 본격 시행",
    "url": "https://www.electimes.com/news/articleView.html?idxno=364392",
    "date": "2026-01-22",
    "tags": [
      "재생에너지",
      "전력계통",
      "출력제어"
    ],
    "subtitle": "육지 최초 재생e·VPP 급전자원화…경부하기 계통 안정성 강화 전력거래소가 재생에너지와 집합전력자원(VPP)을 급전자원으로 활용하는 ‘재생에너지 준중앙급전 운영제도’를 오는 봄철부터 본격 시행한다. 전력수요가 낮은 경부하기에 재생에너지를 계통 운영에 적극 활용해 전력계통 안정성을 높이기 위한 조치다.",
    "is_important": 1
  },
  {
    "source": "전기신문",
    "title": "전기안전공사, 한성대와 ‘ESG 공공-민간 협력’ 손 잡아",
    "url": "https://www.electimes.com/news/articleView.html?idxno=364422",
    "date": "2026-01-22",
    "tags": [
      "재생에너지",
      "ESS"
    ],
    "subtitle": "자원재활용 캠페인, 재생에너지 분야 일자리 탐색 기회 제공 등 협력키로 전기안전공사와 한성대학교가 ESG경영 분야 공공·민간 협력에 앞장선다. 한국전기안전공사(사장 남화영)와 한성대학교(총장 이창원)는 22일 서울 한성대학교 상상관에서 ‘ESG경영 실천과 에너지신산업 분야 인재 양성을 위한 업무협약’을 맺었다고 밝혔다.",
    "is_important": 1
  },
  {
    "source": "전기신문",
    "title": "볼보차, 신규 아키텍처 SPA3로 만든 중형 SUV 'EX60' 공개…배터리 10년 보증",
    "url": "https://www.electimes.com/news/articleView.html?idxno=364417",
    "date": "2026-01-22",
    "tags": [
      "배터리"
    ],
    "subtitle": "볼보자동차가 완전히 새로운 중형 SUV로 전동화 전략을 본격적으로 확대한다. 볼보는 21일(현지 시각) 스웨덴 스톡홀름에서 EX60을 공개했다.",
    "is_important": 1
  },
  {
    "source": "전기신문",
    "title": "반도체·전력·에너지주 힘 보태며 코스피 사상 첫 5000선 돌파",
    "url": "https://www.electimes.com/news/articleView.html?idxno=364397",
    "date": "2026-01-22",
    "tags": [
      "원자력",
      "재생에너지",
      "ESS",
      "데이터센터"
    ],
    "subtitle": "글로벌 유동성 회복 속 전력·에너지주 존재감 부각 설비 투자·에너지 전환 기대가 지수 하단 지지 전력망·신재생·원전주까지 확산된 상승 흐름 글로벌 유동성 회복과 산업 기대감이 맞물리며 코스피 지수가 최초로 장중 5000선을 돌파했다. 반도체, 방산과 함께 전력·에너지 관련주가 동반 강세를 보이며 지수 상승의 또 다른 축으로 작용했다는 평가다.",
    "is_important": 1
  },
  {
    "source": "전기신문",
    "title": "남부발전, 재생에너지 Power-Up 워크숍 개최…협업방안 모색",
    "url": "https://www.electimes.com/news/articleView.html?idxno=364419",
    "date": "2026-01-22",
    "tags": [
      "재생에너지",
      "NDC"
    ],
    "subtitle": "재생에너지 주력 전원화 위한 실행력 강화 남부발전 재생에너지본부 임직원이 재생에너지의 주력 전원화를 위한 실행력 강화 차원에서 머리를 맞댔다. 22일 한국남부발전(사장 김준동)은 세종 컨벤션센터에서 재생에너지 확대와 에너지 전환 선도를 위한 ‘KOSPO, 재생에너지 Power-Up 워크숍’을 개최했다고 밝혔다.",
    "is_important": 1
  },
  {
    "source": "전기신문",
    "title": "기후부, 전기지게차 구매지원 신설…건설기계 전동화 속도",
    "url": "https://www.electimes.com/news/articleView.html?idxno=364383",
    "date": "2026-01-22",
    "tags": [
      "기후부",
      "탄소중립"
    ],
    "subtitle": "“수송 부문 탄소중립 위해 전동화 필요…세부 이행계획 구체화할 것” 정부가 전기지게차 구매지원 신설을 통해 건설기계 전동화에 속도를 낸다. 기후에너지환경부는 무공해 건설기계 보급을 촉진하기 위해 ‘2026년 무공해 건설기계 보급사업 보조금 업무처리지침’과 ‘2026년 무공해 건설현장 지원사업 보조금 업무처리지침’ 개편안을 확정하고, 오는 23일부터 시행한다고 22일 밝혔다.",
    "is_important": 1
  },
  {
    "source": "전기신문",
    "title": "기후부, 올해 전기차 충전시설 예산 5457억원…‘양보다 질’에 방점",
    "url": "https://www.electimes.com/news/articleView.html?idxno=364381",
    "date": "2026-01-22",
    "tags": [
      "기후부"
    ],
    "subtitle": "최소 성능기준 도입·강화로 충전 품질 및 이용 신뢰성 제고 정부가 전기차 충전기의 양적 확대 중심 정책에서 벗어나 품질 향상에 방점을 찍고 지원에 나선다. 기후에너지환경부는 ‘2026년도 전기차 충전 기반시설 구축 사업’을 본격 추진한다고 22일 밝혔다.",
    "is_important": 1
  },
  {
    "source": "전기신문",
    "title": "‘송전 없는 지산지소’라는 허상",
    "url": "https://www.electimes.com/news/articleView.html?idxno=364319",
    "date": "2026-01-22",
    "tags": [
      "재생에너지",
      "데이터센터"
    ],
    "subtitle": "‘햇빛소득마을’을 반기는 이들이 동시에 송전탑 건설 반대 운동에 몸담고 있는 장면을 마주할 때 만감이 교차했다. 태양광을 통해 에너지자립의 주체가 되고 안정적인 소득을 기대하다가도, ‘에너지고속도로’가 도마 위에 오르면 일순 공기가 싸늘해진다.",
    "is_important": 1
  },
  {
    "source": "전기신문",
    "title": "‘wire·Tube 2026’서 글로벌 와이어·튜브 산업의 미래를 보다",
    "url": "https://www.electimes.com/news/articleView.html?idxno=364384",
    "date": "2026-01-22",
    "tags": [
      "수소"
    ],
    "subtitle": "4월 13일–17일 독일 뒤셀도르프 개최, 65개국 2,700개 기업 참가 수소·e-모빌리티·AI·에너지 전환 등 핵심 산업 트렌드 집중 조명 韓서도 한화솔루션 등 23개사 참가...글로벌 무대서 기술력 과시 와이어·케이블, 튜브·파이프 산업의 최신 기술과 글로벌 산업 트렌드를 한 자리에서 확인할 수 있는 ‘wire·Tube 2026’ 전시회가 오는 4월 13일부터 17일까지 독일 뒤셀도르프에서 열린다. 이번 전시회에는 65개국 2,700개 기업이 참가해 약 12만㎡에 달하는 전시장에서 최신 기술과 솔루션을 선보일 예정이다.",
    "is_important": 1
  },
  {
    "source": "전기신문",
    "title": "(데스크시선)부산시 7차 지역에너지계획과 양치기 소년",
    "url": "https://www.electimes.com/news/articleView.html?idxno=364189",
    "date": "2026-01-22",
    "tags": [
      "재생에너지",
      "수용성"
    ],
    "subtitle": "이솝 우화 속 ‘양치기 소년’은 거짓말을 거듭한 끝에 신뢰를 잃었다. 부산시의 제7차 지역에너지계획이 이 비유로 읽히는 이유도 다르지 않다.",
    "is_important": 1
  },
  {
    "source": "전기신문",
    "title": "\"영농형태양광, 확대 논의 넘어 ‘지속 가능한 설계’로 향해야\"",
    "url": "https://www.electimes.com/news/articleView.html?idxno=364374",
    "date": "2026-01-22",
    "tags": [
      "재생에너지",
      "ESS",
      "충전소",
      "REC"
    ],
    "subtitle": "‘지역 공존 재생E 보급 확대 세미나’서 제도 보완 모색 임차농 소외 등 농촌 현장 부작용 공론장 위로 “보급의 목적, 재생에너지 확대보다 농업 위기 타개” 이격거리 규제·REC 수익구조 등 저해요소 개선 목소리 영농형태양광 도입 과정에서 농촌과 지역 현장의 목소리를 반영한 정교한 제도 설계가 선행돼야 한다는 지적이 제기된다. 단순 보급 확대 논의를 넘어서 도시와 농촌 간의 책임 분담, 수익 분배의 공정성을 확보하고 실질적인 지역 공존형 모델을 마련해야 한다는 목소리도 나온다.",
    "is_important": 1
  },
  {
    "source": "에너지신문",
    "title": "한수원, 中企와 손잡고 美 원전시장 본격 공략",
    "url": "https://www.energy-news.co.kr/news/articleView.html?idxno=222196",
    "date": "2026-01-22",
    "tags": [
      "원자력",
      "한수원"
    ],
    "subtitle": "[에너지신문] 한국수력원자력이 18~24일(현지시간) 16개 협력 중소기업과 함께 미국 텍사스주에서 ‘MANUGA with K’ 사업을 통해 미국 원전산업 선점을 위한 지원활동을 펼친다. MANUGA(Make America NUuclear cooperation Great Again) with K는 미국의 원자력 발전 확대 계획으로 국내 원전기업의 미국시장 참여 기회 확대가 기대됨에 따라 협력 중소기업의 북미시장 진출을 돕기위해 한수원이 야심차게 추진하고 있는 사업이다.",
    "is_important": 1
  },
  {
    "source": "에너지신문",
    "title": "제주도, 분산에너지 기반 전력 활용 모델 구축… V2G 실증",
    "url": "https://www.energy-news.co.kr/news/articleView.html?idxno=222188",
    "date": "2026-01-22",
    "tags": [
      "재생에너지",
      "ESS",
      "배터리",
      "전력계통",
      "출력제어"
    ],
    "subtitle": "[에너지신문] 전기차로 전기를 충전만 하던 시대가 끝나고 저장했던 전기를 다시 팔 수 있는 시대가 열린다. 제주가 그 첫 실험 무대다.",
    "is_important": 1
  },
  {
    "source": "에너지신문",
    "title": "전기안전공사, ‘ESG 공공-민간 협력’ 첫 걸음",
    "url": "https://www.energy-news.co.kr/news/articleView.html?idxno=222223",
    "date": "2026-01-22",
    "tags": [
      "재생에너지",
      "ESS"
    ],
    "subtitle": "[에너지신문] 한국전기안전공사가 한성대학교와 손잡고 ESG경영 분야 민간-공공 협력의 새 길을 연다. 전기안전공사는 22일 한성대와 ‘ESG경영 실천과 에너지신산업 분야 인재 양성을 위한 업무협약’을 맺었다.",
    "is_important": 1
  },
  {
    "source": "에너지신문",
    "title": "재생E 준중앙급전 운영제도, 봄부터 본격 운영",
    "url": "https://www.energy-news.co.kr/news/articleView.html?idxno=222189",
    "date": "2026-01-22",
    "tags": [
      "재생에너지",
      "전력계통"
    ],
    "subtitle": "[에너지신문] 전력거래소는 육지 전력계통의 안정적인 운영을 위해 ‘재생에너지 준중앙급전 운영제도’를 봄철부터 본격 시행한다. 재생E 준중앙급전 운영제도는 전력수요가 낮은 봄·가을철 경부하기에 전력계통을 안정적으로 운영하기 위해 마련된 제도.",
    "is_important": 1
  },
  {
    "source": "에너지신문",
    "title": "이콜랩, CDP 수자원 관리‧기후변화 대응 평가 ‘최고 등급’",
    "url": "https://www.energy-news.co.kr/news/articleView.html?idxno=222187",
    "date": "2026-01-22",
    "tags": [
      "데이터센터"
    ],
    "subtitle": "[에너지신문] 물, 위생 및 감염 예방 분야에서 ESG 통합 솔루션을 제공하는 글로벌 화학기업 이콜랩이 글로벌 기후변화 대응 평가기관 ‘탄소정보공개프로젝트(CDP)’ 평가에서 수자원 관리 부문 7년 연속, 기후변화 대응 부문 5년 연속 최고 등급인 ‘리더십 A’를 획득했다. CDP는 전 세계 주요 기업을 대상으로 기후변화 대응 전략, 온실가스 배출 및 감축 성과, 수자원 관리 체계, 정보 공개 수준 등을 종합 평가하는 비영리 국제기구다.",
    "is_important": 1
  },
  {
    "source": "에너지신문",
    "title": "바이오가스 생산목표제, 올해 민간부문으로 확대",
    "url": "https://www.energy-news.co.kr/news/articleView.html?idxno=222221",
    "date": "2026-01-22",
    "tags": [
      "수소",
      "기후부",
      "배터리",
      "충전소",
      "수소버스",
      "수소차",
      "전력계통",
      "탄소중립",
      "수용성",
      "바이오가스"
    ],
    "subtitle": "[에너지신문] 공공부문에 이어 바오가스 생산목표제가 올해부터 민간부문으로 확대 시행된다. 돼지 사육두수 2만5000두 이상 가축분뇨 배출자, 국가 또는 지자체 지원 받은 처리용량 200㎥/일 이상인 가축분뇨 처리시설(돈분 80% 이상) 운영자, 연간 1000톤 이상의 음식물류 폐기물 배출자 등 민간 의무생산자는 가축분뇨, 음식물류폐기물 등 처리 책임이 있는 유기성 폐자원을 활용해 생산목표(2026년 10%)만큼 바이오가스를 생산해야 된다.",
    "is_important": 1
  },
  {
    "source": "에너지신문",
    "title": "미래엔서해에너지, 2026 무사고ㆍ무재해 ‘안전기원 산행’ 실시",
    "url": "https://www.energy-news.co.kr/news/articleView.html?idxno=222206",
    "date": "2026-01-22",
    "tags": [
      "도시가스"
    ],
    "subtitle": "[에너지신문] 미래엔서해에너지(대표이사 송민섭)는 21일 2026년 병오년 새해를 맞아 무사고ㆍ무재해를 염원하는 ‘2026년 안전기원 산행’을 실시했다고 밝혔다. 이번 산행은 충남 당진시 소재 아미산에서 진행됐으며, 김충식 상무를 비롯한 임직원 30여 명이 참석해 한 해 동안의 무사고ㆍ무재해 달성을 기원하고, 안전을 최우선 가치로 하는 경영 실천 의지를 다시 한 번 다졌다.",
    "is_important": 1
  },
  {
    "source": "에너지신문",
    "title": "대성에너지, 산업안전보건 체계 고도화 워크숍 실시",
    "url": "https://www.energy-news.co.kr/news/articleView.html?idxno=222208",
    "date": "2026-01-22",
    "tags": [
      "도시가스"
    ],
    "subtitle": "[에너지신문] 대성에너지는 22일 서부지사 강당에서 팀별 Keyman과 관리감독자 30여명을 대상으로 ‘산업안전보건 체계 고도화 위험성평가 워크숍’을 실시했다. 위험성평가는 작업이나 활동에서 발생할 수 있는 유해·위험요인을 체계적으로 식별하고, 발생 가능성과 심각도을 분석·추정해 위험도를 산정한 뒤 이를 허용 가능한 수준으로 낮추기 위한 통제·개선대책을 결정하고 실행하는 전 과정을 말한다.",
    "is_important": 1
  },
  {
    "source": "에너지신문",
    "title": "기후솔루션, NCC공정 전기화시 ‘수소화‘ 대비 비용 절반",
    "url": "https://www.energy-news.co.kr/news/articleView.html?idxno=222218",
    "date": "2026-01-22",
    "tags": [
      "수소",
      "그린수소",
      "재생에너지",
      "NDC",
      "탄소중립"
    ],
    "subtitle": "[에너지신문] 나프타 분해 공정(NCC)을 전기화하게 될 경우 기존 수소화 방식 대비 비용이 절반 수준으로 최대 약 128조원 아낄 수 있다는 분석이 나왔다. 현재 석유화학특별법 제정으로 탄소중립과 공급과잉이라는 위기를 타개하려는 공감대가 형성된 가운데 범용 제품 생산량을 25% 감축하는 구조조정이 진행중인 상태다.",
    "is_important": 1
  },
  {
    "source": "에너지신문",
    "title": "기후부, 취약계층 에너지복지 지원 현장 점검",
    "url": "https://www.energy-news.co.kr/news/articleView.html?idxno=222219",
    "date": "2026-01-22",
    "tags": [
      "기후부"
    ],
    "subtitle": "[에너지신문] 겨울철 난방비 부담으로 어려움을 겪는 취약계층이 보다 따뜻한 겨울을 보낼 수 있도록 기후에너지환경부가 에너지복지 지원 현장에서 실태를 점검하고 현장의 목소리를 듣는다. 기후부는 오일영 기후에너지정책실장이 22일 사회복지법인 서울 삼성원을 방문했다고 밝혔다.",
    "is_important": 1
  },
  {
    "source": "에너지신문",
    "title": "“열에너지 정책 없인 탄소중립 달성 불가능”",
    "url": "https://www.energy-news.co.kr/news/articleView.html?idxno=222191",
    "date": "2026-01-22",
    "tags": [
      "재생에너지",
      "히트펌프",
      "도시가스",
      "NDC",
      "탄소중립"
    ],
    "subtitle": "[에너지신문] 전력 중심으로 움직여왔던 에너지정책에 ‘열에너지’ 정책이 필요하다는 주장이 수면으로 부상하고, 이에 관한 법안이 발의되면서 ‘뜨거운 감자’로 떠올랐다. 국내 최종에너지 소비의 48%가 난방·냉방·공정열 등 ‘열에너지’에서 발생하고 있는데도 열에너지 부문에 대한 명확한 정책없이 방치돼 왔다.",
    "is_important": 1
  },
  {
    "source": "가스신문",
    "title": "정부의 공기열 히트펌프 재생에너지 인정 확대 “너무 앞선 정책”",
    "url": "https://www.gasnews.com/news/articleView.html?idxno=123679",
    "date": "2026-01-22",
    "tags": [
      "재생에너지",
      "히트펌프",
      "탄소중립",
      "수용성"
    ],
    "subtitle": "[가스신문 = 주병국 기자] 정부가 추진 중인 공기열 히트펌프의 재생에너지 인정 확대를 둘러싼 문제점집중적으로 논의하고, 대안을 찾는 토론회가 국회에서 열렸다. 국회 기후에너지환경노동위원회 김소희 의원(국민의힘)이 1월 21일 국회에서 ‘히트펌프 과연 재생에너지인가?’라는 주제로 학계 및 에너지 전문가들을 초청한 가운데 토론회를 개최됐다.",
    "is_important": 1
  },
  {
    "source": "가스신문",
    "title": "에너지정의행동 “에너지정책, 인기투표로 정할 수 없어”",
    "url": "https://www.gasnews.com/news/articleView.html?idxno=123683",
    "date": "2026-01-22",
    "tags": [
      "재생에너지"
    ],
    "subtitle": "[가스신문 = 유재준 기자] 22일 환경시민단체인 에너지정의행동은 “제12차 전기본을 비롯한 국가의 에너지정책은 호감도 조사로 결정할 수 있는 문제가 아니다. 정부는 여론조사 숫자 뒤에 숨지말고 진정한 숙의를 통한 책임있는 정책으로 나아가야 한다”고 밝혔다.",
    "is_important": 1
  },
  {
    "source": "가스신문",
    "title": "수소동력 무인항공기, 우크라이나 전투 작전 돌입",
    "url": "https://www.gasnews.com/news/articleView.html?idxno=123673",
    "date": "2026-01-22",
    "tags": [
      "수소",
      "연료전지"
    ],
    "subtitle": "[가스신문 = 양인범 기자] H2뷰에 따르면 드론 제조업체 스카이톤(Skyeton)은 수소 연료전지로 구동되는 무인 항공기(UAV)가 우크라이나 방위군 부대와 함께 전면 전투에 돌입했다고 확인했다. 이 회사는 적응형 레이버드 UAS가 기관 간 테스트의 일환으로 12월부터 전투 지역에서 임무를 수행하고 있다고 밝혔다.",
    "is_important": 1
  },
  {
    "source": "가스신문",
    "title": "성동구, 올해 ‘가정용 친환경보일러 설치 지원사업’ 지속",
    "url": "https://www.gasnews.com/news/articleView.html?idxno=123685",
    "date": "2026-01-22",
    "tags": [
      "탄소중립"
    ],
    "subtitle": "[가스신문 = 양인범 기자] 서울 성동구(구청장 정원오)는 21일 민관협력을 통해 ‘가정용 친환경보일러 설치 지원 사업’을 올해도 지속 추진한다고 밝혔다. ‘가정용 친환경보일러 설치 지원 사업’은 노후화된 가정용 보일러를 연료비 절감 효과가 큰 친환경 보일러로 교체 또는 신규 설치하는 경우 설치비용 일부를 지원하는 사업이다.",
    "is_important": 1
  },
  {
    "source": "가스신문",
    "title": "복합열설비 폐열까지 청정열로 규정한 법안에 ‘찬반’ 논쟁 뜨거워",
    "url": "https://www.gasnews.com/news/articleView.html?idxno=123681",
    "date": "2026-01-22",
    "tags": [
      "재생에너지",
      "히트펌프",
      "도시가스",
      "탄소중립"
    ],
    "subtitle": "22일 열에너지 탈탄소화 촉진법 입법 공청회 [가스신문 = 주병국 기자] 열전기융합설비, 열전기동시생산설비 또는 복합열설비에서 생산되는 폐열도 ‘청정열’로 인정하는 열에너지기본법 개정안을 놓고 국회에서 ‘찬반’ 논쟁이 벌어졌다. 국회 위성곤 의원 ( 더불어민주당 ) 이 주최하는 ‘열에너지기본법 및 열에너지 탈탄소화 촉진법 입법’ 공청회가 22일 국회 제2세미나실에서 집단에너지업계와 도시가스업계가 참석한 가운데 열렸다.",
    "is_important": 1
  },
  {
    "source": "가스신문",
    "title": "미래엔서해에너지, '무사고ㆍ무재해' 안전기원 산행’",
    "url": "https://www.gasnews.com/news/articleView.html?idxno=123682",
    "date": "2026-01-22",
    "tags": [
      "도시가스"
    ],
    "subtitle": "[가스신문 = 주병국 기자] 미래엔서해에너지(대표이사 송민섭)는 지난 21일, 2026년 병오년 새해를 맞아 무사고ㆍ무재해를 염원하는 ‘2026년 안전기원 산행’을 실시했다고 22일 밝혔다. 이번 산행은 충남 당진시 소재 아미산에서 진행됐으며, 김충식 상무를 비롯한 임직원 30여 명이 참석해 한 해 동안의 무사고ㆍ무재해 달성을 기원하고, 안전을 최우선 가치로 하는 경영 실천 의지를 다시 한 번 다졌다.",
    "is_important": 1
  },
  {
    "source": "가스신문",
    "title": "노르드솔, 노르웨이 공장에 바이오LNG 기술 공급",
    "url": "https://www.gasnews.com/news/articleView.html?idxno=123672",
    "date": "2026-01-22",
    "tags": [
      "바이오가스"
    ],
    "subtitle": "[가스신문 = 양인범 기자] 가스월드에 따르면 네덜란드에 본사를 둔 바이오 LNG 회사 노르드솔(Nordsol)은 노르웨이 남부 파르순드에 위치한 리스타 바이오가스 공장에 바이오가스 개질 및 액화 장비를 제공하게 된다. 청정 에너지 개발업체 비레오가 소유하고 운영하는 이 공장은 운송 및 산업 부문을 위해 연간 약 90GWh의 화석 연료 없는 바이오 LNG를 생산할 예정이다.",
    "is_important": 1
  },
  {
    "source": "가스신문",
    "title": "기후부, 취약계층 에너지복지 지원 현장 점검",
    "url": "https://www.gasnews.com/news/articleView.html?idxno=123676",
    "date": "2026-01-22",
    "tags": [
      "기후부"
    ],
    "subtitle": "[가스신문 = 양인범 기자] 겨울철 난방비 부담으로 어려움을 겪는 취약계층이 보다 따뜻한 겨울을 보낼 수 있도록 기후에너지환경부가 에너지복지 지원 현장에서 실태를 점검하고 현장의 목소리를 들었다. 기후에너지환경부(장관 김성환) 오일영 기후에너지정책실장이 22일 사회복지법인 서울 삼성원(서울 동작구 소재)을 방문했다.",
    "is_important": 1
  },
  {
    "source": "가스신문",
    "title": "[시론] 미래 전략 자산으로서의 가스 인프라",
    "url": "https://www.gasnews.com/news/articleView.html?idxno=123669",
    "date": "2026-01-22",
    "tags": [
      "수소",
      "재생에너지",
      "도시가스",
      "CCU",
      "CCUS",
      "데이터센터",
      "탄소중립"
    ],
    "subtitle": "대한민국 에너지 산업의 근간을 이루는 가스 인프라는 수십 년간 축적된 막대한 국부(國富)이자 국가 경쟁력의 원천이다. 2024년 연결 재무제표 기준 자산총계가 57조 원을 상회하는 한국가스공사는 전국을 연결하는 5,346km의 주배관망과 평택, 인천 등 5개 기지에 세계 최고 수준의 저장 설비를 보유하고 있다.",
    "is_important": 1
  },
  {
    "source": "가스신문",
    "title": "KAIST, 귀금속 줄이며 수소 생산·연료전지 향상 촉매 구조 개발",
    "url": "https://www.gasnews.com/news/articleView.html?idxno=123677",
    "date": "2026-01-22",
    "tags": [
      "수소",
      "연료전지",
      "수전해"
    ],
    "subtitle": "[가스신문 = 양인범 기자] 촉매는 수소를 만들고 전기를 생산하는 과정을 좌우하는 수소 에너지의 ‘보이지 않는 엔진’이다. 기존 촉매는 만들기 쉬운 알갱이 형태였지만 귀금속을 비효율적으로 쓰고 수명이 짧다는 한계가 있었다.",
    "is_important": 1
  }
]