[
  {
    "source": "전기신문",
    "title": "[석탄전환의 두 얼굴 ⑦]탈석탄 드라이브 속 시한폭탄이 된 산단 노후 석탄열병합",
    "url": "https://www.electimes.com/news/articleView.html?idxno=363741",
    "date": "2026-01-07",
    "tags": [
      "수소",
      "재생에너지",
      "배출권",
      "히트펌프",
      "구역전기",
      "SMP"
    ],
    "subtitle": "탈석탄 전환 속 연료 선택지 좁아져…LNG마저 난항 재생에너지·수소·히트펌프, 산단 적용엔 구조적 제약 정부가 2040년까지 석탄화력발전소를 전면 폐쇄하겠다는 방침을 공식화하면서 탈석탄 정책에 속도가 붙고 있다. 그러나 이 같은 정책 흐름의 이면에는 상대적으로 덜 조명된 취약 지점이 존재한다.",
    "is_important": 1
  },
  {
    "source": "에너지신문",
    "title": "중부발전, 2026 업무보고...\"국민체감 성과 창출\"",
    "url": "https://www.energy-news.co.kr/news/articleView.html?idxno=221742",
    "date": "2026-01-07",
    "tags": [
      "탄소중립"
    ],
    "subtitle": "[에너지신문] 한국중부발전은 6일 본사에서 경영진이 참석한 가운데 ‘2026년도 본사 업무보고’ 를 가졌다. 이번 업무보고는 정부 출범 이후 변화된 국정운영 방향에 연계, 수립된 회사의 경영전략과 부서별 실행과제를 점검하기 위해 연초에 마련됐다.",
    "is_important": 1
  },
  {
    "source": "에너지신문",
    "title": "‘2026 전력시장 변화와 기업 대응 전략 세미나’ 열린다",
    "url": "https://www.energy-news.co.kr/news/articleView.html?idxno=221741",
    "date": "2026-01-07",
    "tags": [
      "재생에너지",
      "ESS",
      "RE100"
    ],
    "subtitle": "[에너지신문] 세미나허브가 주최하고 한국인프라가 후원하는 ‘에너지전환 시대, 2026 전력시장 변화와 기업 대응 전략 세미나’가 오는 20일 여의도 FKI타워 컨퍼런스센터에서 개최된다. 재생에너지 보급 확대와 전력 수요 구조 변화에 따라 전력시장과 전력공급체계 전반에 걸친 제도 개선과 운영 방식 변화에 대한 논의가 이어지고 있다.",
    "is_important": 1
  },
  {
    "source": "가스신문",
    "title": "울릉군 LPG배관망 저장탱크에 첫 가스 충전",
    "url": "https://www.gasnews.com/news/articleView.html?idxno=123475",
    "date": "2026-01-07",
    "tags": [
      "도시가스"
    ],
    "subtitle": "[가스신문 = 김재형 기자] 울릉군 LPG배관망 구축사업이 본격적인 가동 단계에 접어들었다. 경북 울릉군이 LPG저장탱크에 첫 가스 충전을 실시하며, 도서 지역에 ‘도시가스급’ 에너지 공급 체계를 구축하는 전환점을 맞았다.",
    "is_important": 1
  }
]